pycake/__init__.py
pycake/__init__.pyc
pycake/__main__.py
pycake/cli.py
pycake/cli.pyc
pycake/cli_utils.py
pycake/cli_utils.pyc
pycake/commands.py
pycake/commands.pyc
pycake/meta.py
pycake/meta.pyc
pycake/options.py
pycake/options.pyc
pycake/__pycache__/__init__.cpython-35.pyc
pycake/__pycache__/__init__.cpython-36.pyc
pycake/__pycache__/__init__.cpython-37.pyc
pycake/__pycache__/__main__.cpython-35.pyc
pycake/__pycache__/__main__.cpython-36.pyc
pycake/__pycache__/__main__.cpython-37.pyc
pycake/__pycache__/cli.cpython-35.pyc
pycake/__pycache__/cli.cpython-36.pyc
pycake/__pycache__/cli.cpython-37.pyc
pycake/__pycache__/cli_utils.cpython-35.pyc
pycake/__pycache__/cli_utils.cpython-36.pyc
pycake/__pycache__/cli_utils.cpython-37.pyc
pycake/__pycache__/commands.cpython-35.pyc
pycake/__pycache__/commands.cpython-36.pyc
pycake/__pycache__/commands.cpython-37.pyc
pycake/__pycache__/meta.cpython-35.pyc
pycake/__pycache__/meta.cpython-36.pyc
pycake/__pycache__/meta.cpython-37.pyc
pycake/__pycache__/options.cpython-35.pyc
pycake/__pycache__/options.cpython-36.pyc
pycake/__pycache__/options.cpython-37.pyc
pycake/app/__init__.py
pycake/app/app.py
pycake/app/release.py
pycake/app_template/cookiecutter.json
pycake/app_template/{{cookiecutter.release}}/apis.py
pycake/app_template/{{cookiecutter.release}}/app.py
pycake/app_template/{{cookiecutter.release}}/.app/manage.yaml
pycake/app_template/{{cookiecutter.release}}/.app/monitor.yaml
pycake/app_template/{{cookiecutter.release}}/.app/{{cookiecutter.app.app_name}}.yaml
pycake/app_template/{{cookiecutter.release}}/config/logging.yaml
pycake/app_template/{{cookiecutter.release}}/lib/servicemesh/__init__.py
pycake/app_template/{{cookiecutter.release}}/lib/servicemesh/commands.py
pycake/app_template/{{cookiecutter.release}}/lib/servicemesh/monitor.py
pycake/app_template/{{cookiecutter.release}}/lib/servicemesh/__pycache__/__init__.cpython-37.pyc
py_cake-0.2.2a3.dist-info/LICENSE
py_cake-0.2.2a3.dist-info/METADATA
py_cake-0.2.2a3.dist-info/WHEEL
py_cake-0.2.2a3.dist-info/entry_points.txt
py_cake-0.2.2a3.dist-info/top_level.txt
py_cake-0.2.2a3.dist-info/RECORD
